abuild/__init__.py
abuild/build.py
abuild/config.py
abuild/hashing.py
abuild/main.py
abuild/parsers.py
abuild/state.py
abuild/tags.py
abuild-0.3.0.dist-info/LICENSE
abuild-0.3.0.dist-info/METADATA
abuild-0.3.0.dist-info/WHEEL
abuild-0.3.0.dist-info/entry_points.txt
abuild-0.3.0.dist-info/top_level.txt
abuild-0.3.0.dist-info/RECORD
