Metadata-Version: 2.1
Name: abuild
Version: 0.3.0
Summary: A simple, language agnostic build tool
Author-email: Ingo Fruend <github@ingofruend.net>
License: BSD-3-Clause
Keywords: language agnostic,build tool,monorepo
License-File: LICENSE
Requires-Dist: typer
Requires-Dist: rich
Requires-Dist: pydantic
Requires-Dist: pyyaml
